philvault_sdk/__init__.py
philvault_sdk/async_client.py
philvault_sdk/client.py
philvault_sdk/errors.py
philvault_sdk-0.1.0.dist-info/METADATA
philvault_sdk-0.1.0.dist-info/WHEEL
philvault_sdk-0.1.0.dist-info/top_level.txt
philvault_sdk-0.1.0.dist-info/RECORD
