Metadata-Version: 2.4
Name: philvault-sdk
Version: 0.1.0
Summary: Python SDK for PhilVault authentication and authorization APIs.
Requires-Python: >=3.8
Requires-Dist: httpx>=0.20
